{"repo": {"timestamp": 1687747961000, "version": 20001, "name": "My First F-Droid Repo Demo", "icon": "icon.png", "address": "https://MyFirstFDroidRepo.org/fdroid/repo", "description": "This is a repository of apps to be used with F-Droid. Applications in this repository are either official binaries built by the original application developers, or are binaries built from source by the admin of f-droid.org using the tools on https://gitlab.com/fdroid."}, "requests": {"install": [], "uninstall": []}, "apps": [{"authorName": "BaronKiko", "categories": ["System", "Theming"], "suggestedVersionCode": "2147483647", "issueTracker": "https://github.com/BaronKiko/LauncherHijack/issues", "license": "Unknown", "name": "Launcher Hijack", "sourceCode": "https://github.com/BaronKiko/LauncherHijack", "summary": "A small Android application to circumvent the default Amazon Fire launcher.", "webSite": "https://github.com/BaronKiko/LauncherHijack", "added": 1687747416000, "icon": "com.baronkiko.launcherhijack.43.png", "packageName": "com.baronkiko.launcherhijack", "lastUpdated": 1687747416000}], "packages": {"com.baronkiko.launcherhijack": [{"added": 1687747416000, "apkName": "LauncherHijackV403.apk", "hash": "d5346fb6d0a28b33e97448a49f34a3093d6f7068a10cc43ba3b4b8313d5a1bd4", "hashType": "sha256", "minSdkVersion": 21, "packageName": "com.baronkiko.launcherhijack", "sig": "2462279381abe49db7dc6baaa90499ed", "signer": "8806ca47172ef2f653ac2dc35d01cbc87af542c8072247ad686526788e172fbb", "size": 1590776, "targetSdkVersion": 28, "uses-permission": [["android.permission.BIND_ACCESSIBILITY_SERVICE", null], ["android.permission.RECEIVE_BOOT_COMPLETED", null], ["android.permission.SYSTEM_ALERT_WINDOW", null], ["android.permission.INSTALL_PACKAGES", null]], "versionCode": 43, "versionName": "4.0.3"}]}}