{
  "commandLine": [
    "/nix/store/c4kay2avxp74gm018zj9v6wf4icazc1f-fdroidserver-2.1.1/bin/fdroid update",
    "--rename-apks",
    "--create-metadata",
    "--pretty"
  ],
  "fdroiddata": {
    "commitId": "d352f4916f65872f0d924326c02e872d5c6e4c61",
    "isDirty": true,
    "modifiedFiles": [
      "repo/index-v1.jar",
      "repo/index-v1.json",
      "repo/index.html",
      "repo/index.jar",
      "repo/index.xml",
      "repo/status/running.json",
      "repo/status/update.json",
      "tmp/apkcache.json"
    ],
    "untrackedFiles": [
      "metadata/com.rossonerd.twointerviewees.yml",
      "repo/com.rossonerd.twointerviewees_140.apk",
      "repo/icons-120/com.rossonerd.twointerviewees.140.png",
      "repo/icons-160/com.rossonerd.twointerviewees.140.png",
      "repo/icons-240/com.rossonerd.twointerviewees.140.png",
      "repo/icons-320/com.rossonerd.twointerviewees.140.png",
      "repo/icons-480/com.rossonerd.twointerviewees.140.png",
      "repo/icons-640/com.rossonerd.twointerviewees.140.png",
      "repo/icons/com.rossonerd.twointerviewees.140.png"
    ]
  },
  "startTimestamp": 1687838985000,
  "subcommand": "update"
}